cutlass_cppgen/__init__.py
cutlass_cppgen/library_defaults.py
cutlass_cppgen/shape.py
cutlass_cppgen/swizzle.py
cutlass_cppgen/backend/__init__.py
cutlass_cppgen/backend/arguments.py
cutlass_cppgen/backend/c_types.py
cutlass_cppgen/backend/compiler.py
cutlass_cppgen/backend/conv2d_operation.py
cutlass_cppgen/backend/epilogue.py
cutlass_cppgen/backend/frontend.py
cutlass_cppgen/backend/gemm_operation.py
cutlass_cppgen/backend/library.py
cutlass_cppgen/backend/memory_manager.py
cutlass_cppgen/backend/operation.py
cutlass_cppgen/backend/reduction_operation.py
cutlass_cppgen/backend/type_hint.py
cutlass_cppgen/backend/evt/__init__.py
cutlass_cppgen/backend/evt/epilogue.py
cutlass_cppgen/backend/evt/backend/__init__.py
cutlass_cppgen/backend/evt/backend/emitter_base.py
cutlass_cppgen/backend/evt/backend/sm100_emitter.py
cutlass_cppgen/backend/evt/backend/sm100_nodes.py
cutlass_cppgen/backend/evt/backend/sm80_emitter.py
cutlass_cppgen/backend/evt/backend/sm80_nodes.py
cutlass_cppgen/backend/evt/backend/sm90_emitter.py
cutlass_cppgen/backend/evt/backend/sm90_nodes.py
cutlass_cppgen/backend/evt/backend/xe12_emitter.py
cutlass_cppgen/backend/evt/backend/xe12_nodes.py
cutlass_cppgen/backend/evt/backend/xe20_emitter.py
cutlass_cppgen/backend/evt/backend/xe20_nodes.py
cutlass_cppgen/backend/evt/frontend/__init__.py
cutlass_cppgen/backend/evt/frontend/frontend_base.py
cutlass_cppgen/backend/evt/frontend/python_ast.py
cutlass_cppgen/backend/evt/ir/__init__.py
cutlass_cppgen/backend/evt/ir/compute_nodes.py
cutlass_cppgen/backend/evt/ir/dag_ir.py
cutlass_cppgen/backend/evt/ir/layout_algorithm.py
cutlass_cppgen/backend/evt/ir/layout_nodes.py
cutlass_cppgen/backend/evt/ir/load_nodes.py
cutlass_cppgen/backend/evt/ir/node.py
cutlass_cppgen/backend/evt/ir/store_nodes.py
cutlass_cppgen/backend/evt/ir/tensor.py
cutlass_cppgen/backend/evt/passes/__init__.py
cutlass_cppgen/backend/evt/passes/graph_drawer.py
cutlass_cppgen/backend/evt/passes/pass_argument_type.py
sycl_tla-0.7.0.dist-info/licenses/LICENSE.txt
sycl_tla-0.7.0.dist-info/METADATA
sycl_tla-0.7.0.dist-info/WHEEL
sycl_tla-0.7.0.dist-info/top_level.txt
sycl_tla-0.7.0.dist-info/RECORD
