Metadata-Version: 2.4
Name: sycl-tla
Version: 0.7.0
Summary: sycl templates for linear algebra
License: BSD-3-Clause
Project-URL: Homepage, https://github.com/intel/sycl-tla
Project-URL: Bug Tracker, https://github.com/intel/sycl-tla/issues
Classifier: Programming Language :: Python :: 3
Classifier: License :: OSI Approved :: BSD License
Classifier: Operating System :: OS Independent
Requires-Python: >=3.8
License-File: LICENSE.txt
Requires-Dist: networkx
Requires-Dist: numpy
Requires-Dist: pydot
Requires-Dist: scipy
Requires-Dist: treelib
Requires-Dist: ml_dtypes
Dynamic: license-file
